rym/cx/__about__.py
rym/cx/__init__.py
rym/cx/core/__init__.py
rym/cx/core/_catalog.py
rym/cx/core/_inventory.py
rym/cx/core/component.py
rym/cx/core/decorator.py
rym/cx/core/entity.py
rym/cx/core/errors.py
rym/cx/core/identifier.py
rym/cx/core/record.py
rym/cx/core/registrar.py
rym/cx/core/spawn.py
rym/cx/core/teardown.py
rym_cx-0.1.2.dist-info/METADATA
rym_cx-0.1.2.dist-info/WHEEL
rym_cx-0.1.2.dist-info/RECORD
